ts_stat_tests/__init__.py
ts_stat_tests/correlation/__init__.py
ts_stat_tests/correlation/algorithms.py
ts_stat_tests/correlation/tests.py
ts_stat_tests/heteroscedasticity/__init__.py
ts_stat_tests/heteroscedasticity/algorithms.py
ts_stat_tests/heteroscedasticity/tests.py
ts_stat_tests/linearity/__init__.py
ts_stat_tests/linearity/algorithms.py
ts_stat_tests/linearity/tests.py
ts_stat_tests/normality/__init__.py
ts_stat_tests/normality/algorithms.py
ts_stat_tests/normality/tests.py
ts_stat_tests/regularity/__init__.py
ts_stat_tests/regularity/algorithms.py
ts_stat_tests/regularity/tests.py
ts_stat_tests/seasonality/__init__.py
ts_stat_tests/seasonality/algorithms.py
ts_stat_tests/seasonality/tests.py
ts_stat_tests/stability/__init__.py
ts_stat_tests/stability/algorithms.py
ts_stat_tests/stability/tests.py
ts_stat_tests/stationarity/__init__.py
ts_stat_tests/stationarity/algorithms.py
ts_stat_tests/stationarity/tests.py
ts_stat_tests/utils/__init__.py
ts_stat_tests/utils/data.py
ts_stat_tests/utils/errors.py
ts_stat_tests-1.0.1.dist-info/WHEEL
ts_stat_tests-1.0.1.dist-info/METADATA
ts_stat_tests-1.0.1.dist-info/RECORD
