Metadata-Version: 2.4
Name: ts-stat-tests
Version: 1.0.1
Summary: A suite of statistical tests for time-series data.
Author: Chris Mahoney
Author-email: Chris Mahoney <ts-stat-tests@data-science-extensions.com>
License-Expression: MIT
Classifier: Development Status :: 5 - Production/Stable
Classifier: License :: OSI Approved :: MIT License
Classifier: Topic :: Utilities
Classifier: Topic :: Scientific/Engineering :: Mathematics
Classifier: Topic :: Scientific/Engineering :: Information Analysis
Classifier: Topic :: Software Development :: Quality Assurance
Classifier: Topic :: Software Development :: Libraries :: Python Modules
Classifier: Topic :: Software Development :: Testing :: Unit
Classifier: Programming Language :: Python :: 3
Classifier: Programming Language :: Python :: 3.10
Classifier: Programming Language :: Python :: 3.11
Classifier: Programming Language :: Python :: 3.12
Classifier: Programming Language :: Python :: 3.13
Classifier: Programming Language :: Python :: 3.14
Classifier: Operating System :: Unix
Classifier: Operating System :: MacOS
Classifier: Operating System :: Microsoft :: Windows
Classifier: Intended Audience :: Developers
Classifier: Intended Audience :: Science/Research
Classifier: Typing :: Typed
Classifier: Natural Language :: English
Requires-Dist: typeguard==4.*
Requires-Dist: antropy==0.1.*
Requires-Dist: llvmlite>=0.44.0
Requires-Dist: numba>=0.61.0
Requires-Dist: numpy>=2.0.0,<2.4.0
Requires-Dist: pandas==2.*
Requires-Dist: scipy==1.*
Requires-Dist: statsmodels==0.14.*
Requires-Dist: tsfeatures==0.4.*
Requires-Dist: pmdarima
Maintainer: Chris Mahoney
Maintainer-email: Chris Mahoney <ts-stat-tests@data-science-extensions.com>
Requires-Python: >=3.10
Project-URL: Homepage, https://github.com/data-science-extensions/ts-stat-tests
Project-URL: Documentation, https://github.com/data-science-extensions/ts-stat-tests/blob/main/README.md
Project-URL: Repository, https://github.com/data-science-extensions/ts-stat-tests
Project-URL: Changelog, https://github.com/data-science-extensions/ts-stat-tests/releases
Project-URL: Issues, https://github.com/data-science-extensions/ts-stat-tests/issues
